janim/__init__.py
janim/__main__.py
janim/cli.py
janim/examples.py
janim/exception.py
janim/imports.py
janim/logger.py
janim/typing.py
janim/anims/anim_stack.py
janim/anims/animation.py
janim/anims/composition.py
janim/anims/creation.py
janim/anims/display.py
janim/anims/fading.py
janim/anims/growing.py
janim/anims/indication.py
janim/anims/method_updater_meta.py
janim/anims/movement.py
janim/anims/rotation.py
janim/anims/timeline.py
janim/anims/transform.py
janim/anims/updater.py
janim/camera/camera.py
janim/camera/camera_info.py
janim/components/component.py
janim/components/data.py
janim/components/depth.py
janim/components/glow.py
janim/components/image.py
janim/components/mark.py
janim/components/points.py
janim/components/radius.py
janim/components/rgbas.py
janim/components/simple.py
janim/components/vpoints.py
janim/constants/__init__.py
janim/constants/alignment.py
janim/constants/colors.py
janim/constants/coord.py
janim/constants/degrees.py
janim/gui/anim_viewer.py
janim/gui/application.py
janim/gui/audio_player.py
janim/gui/capture.png
janim/gui/collapse_tip1.png
janim/gui/collapse_tip2.png
janim/gui/export.png
janim/gui/favicon.ico
janim/gui/fixed_ratio_widget.py
janim/gui/glwidget.py
janim/gui/label.py
janim/gui/precise_timer.py
janim/gui/timeline_view.py
janim/gui/functions/CaptureDialog.ui
janim/gui/functions/ColorWidget.ui
janim/gui/functions/ExportDialog.ui
janim/gui/functions/capture_dialog.py
janim/gui/functions/color_widget.py
janim/gui/functions/export_dialog.py
janim/gui/functions/font_table.py
janim/gui/functions/painter.py
janim/gui/functions/richtext_editor.py
janim/gui/functions/search.png
janim/gui/functions/selector.py
janim/gui/functions/text_edit.py
janim/gui/functions/ui_CaptureDialog.py
janim/gui/functions/ui_ColorWidget.py
janim/gui/functions/ui_ExportDialog.py
janim/items/audio.py
janim/items/boolean_ops.py
janim/items/frame_effect.py
janim/items/image_item.py
janim/items/item.py
janim/items/points.py
janim/items/relation.py
janim-3.10.2.dist-info/entry_points.txt
janim-3.10.2.dist-info/licenses/LICENSE
janim-3.10.2.dist-info/WHEEL
janim-3.10.2.dist-info/METADATA
janim-3.10.2.dist-info/RECORD
