Metadata-Version: 2.4
Name: janim
Version: 3.10.2
Summary: A library for creating smooth animations
Author: jkjkil4
Requires-Python: >=3.12
Classifier: Programming Language :: Python
License-File: LICENSE
Requires-Dist: attrs
Requires-Dist: numpy
Requires-Dist: pyquaternion
Requires-Dist: colour
Requires-Dist: rich
Requires-Dist: moderngl
Requires-Dist: PyOpenGL
Requires-Dist: tqdm
Requires-Dist: psutil
Requires-Dist: skia-pathops
Requires-Dist: fontTools
Requires-Dist: freetype-py
Requires-Dist: pillow
Requires-Dist: svgelements
Requires-Dist: sphinx ; extra == "doc"
Requires-Dist: sphinx-copybutton ; extra == "doc"
Requires-Dist: sphinx-tabs ; extra == "doc"
Requires-Dist: furo ; extra == "doc"
Requires-Dist: jinja2 ; extra == "doc"
Requires-Dist: docutils ; extra == "doc"
Requires-Dist: pyside6 ; extra == "gui"
Requires-Dist: qdarkstyle ; extra == "gui"
Requires-Dist: beautifulsoup4 ; extra == "gui"
Requires-Dist: pyaudio ; extra == "gui" and ( sys_platform == 'win32')
Requires-Dist: opencv-python ; extra == "test"
Project-URL: Documentation, https://janim.rtfd.io
Project-URL: Home, https://github.com/jkjkil4/JAnim
Project-URL: Source, https://github.com/jkjkil4/JAnim
Provides-Extra: doc
Provides-Extra: gui
Provides-Extra: test
